at_client_workflow/__init__.py
at_client_workflow/client/__init__.py
at_client_workflow/client/base.py
at_client_workflow/client/prompt.py
at_client_workflow/schema/__init__.py
at_client_workflow/schema/prompt.py
at_client_workflow/schema/workflow.py
at_client_workflow-0.1.5.dist-info/METADATA
at_client_workflow-0.1.5.dist-info/WHEEL
at_client_workflow-0.1.5.dist-info/top_level.txt
at_client_workflow-0.1.5.dist-info/RECORD
